{
  "prepare_queue": {
    "installed": [],
    "uninstalled": []
  },
  "config_munge": {
    "files": {}
  },
  "installed_plugins": {
    "cordova-plugin-whitelist": {
      "PACKAGE_NAME": "io.cordova.hellocordova"
    },
    "cordova-plugin-clipboard-x": {
      "PACKAGE_NAME": "io.cordova.hellocordova"
    },
    "nl.madebymark.share": {
      "PACKAGE_NAME": "io.cordova.hellocordova"
    },
    "cordova-plugin-network-information": {
      "PACKAGE_NAME": "io.cordova.hellocordova"
    }
  },
  "dependent_plugins": {}
}
